accordian.py
accordian-0.4.0.dist-info/LICENSE
accordian-0.4.0.dist-info/METADATA
accordian-0.4.0.dist-info/WHEEL
accordian-0.4.0.dist-info/top_level.txt
accordian-0.4.0.dist-info/RECORD
