Metadata-Version: 2.1
Name: accordian
Version: 0.4.0
Summary: Event dispatch in Python 3.8 using asyncio
Home-page: http://github.com/numberoverzero/accordian/
Author: Joe Cross
Author-email: joe.mcross@gmail.com
License: MIT
Keywords: async asyncio dispatch
Platform: any
Classifier: Development Status :: 3 - Alpha
Classifier: Intended Audience :: Developers
Classifier: License :: OSI Approved :: MIT License
Classifier: Programming Language :: Python :: 3.8
Classifier: Topic :: Software Development :: Libraries :: Python Modules
